de_utils_pierrealexandre78/__init__.py
de_utils_pierrealexandre78/cat.py
de_utils_pierrealexandre78/main.py
de_utils_pierrealexandre78-0.1.1.dist-info/METADATA
de_utils_pierrealexandre78-0.1.1.dist-info/WHEEL
de_utils_pierrealexandre78-0.1.1.dist-info/entry_points.txt
de_utils_pierrealexandre78-0.1.1.dist-info/top_level.txt
de_utils_pierrealexandre78-0.1.1.dist-info/RECORD
